proxy_validator/__init__.py
proxy_validator/proxy_type.py
proxy_validator/settings.py
proxy_validator/validator.py
proxy_validator-0.2.5.dist-info/WHEEL
proxy_validator-0.2.5.dist-info/METADATA
proxy_validator-0.2.5.dist-info/RECORD
