Metadata-Version: 2.1
Name: proxy-validator
Version: 0.2.5
Summary: Utility for proxy validation
Author: nash
Author-email: nash@fixmost.com
Requires-Python: >3.6
Classifier: Programming Language :: Python :: 3
Classifier: Programming Language :: Python :: 3.7
Classifier: Programming Language :: Python :: 3.8
Classifier: Programming Language :: Python :: 3.9
Requires-Dist: PySocks (>=1.7.1,<2.0.0)
Requires-Dist: requests (>=2.24.0)
